{"fields":[{"name":"region","format":"","type":"string"},{"name":"city","format":"","type":"string"},{"name":"day","format":"YYYY-M-D H:m:s","type":"timestamp"},{"name":"latitude","format":"","type":"real"},{"name":"longitude","format":"","type":"real"},{"name":"waste_weight","format":"","type":"integer"}],"row":[["thane","airoli","2021-3-28 22:18:53",19.159948163102086,72.99900623858116,11],["thane","airoli","2021-3-29 1:13:59",19.159948163102086,72.99900623858116,5],["thane","airoli","2021-3-29 1:18:6",19.159948163102086,72.99900623858116,11],["nashik","mhasrul","2021-3-31 12:9:42",20.05417693324374,73.80762146941404,8.79],["thane","ghansoli","2021-3-31 21:43:42",20.05417693324374,73.80762146941404,5]]}